setup.py
crawlite/__init__.py
crawlite.egg-info/PKG-INFO
crawlite.egg-info/SOURCES.txt
crawlite.egg-info/dependency_links.txt
crawlite.egg-info/requires.txt
crawlite.egg-info/top_level.txt
crawlite/__pycache__/__init__.cpython-310.pyc
crawlite/__pycache__/__init__.cpython-38.pyc
crawlite/__pycache__/__main__.cpython-38.pyc
crawlite/__pycache__/settings.cpython-310.pyc
crawlite/__pycache__/settings.cpython-38.pyc
crawlite/__pycache__/visitors.cpython-38.pyc
crawlite/core/__init__.py
crawlite/core/__pycache__/__init__.cpython-310.pyc
crawlite/core/__pycache__/__init__.cpython-38.pyc
crawlite/core/http/__init__.py
crawlite/core/http/adapters.py
crawlite/core/http/cached_request.py
crawlite/core/http/curl.py
crawlite/core/http/exceptions.py
crawlite/core/http/helper.py
crawlite/core/http/utils.py
crawlite/core/http/__pycache__/__init__.cpython-310.pyc
crawlite/core/http/__pycache__/__init__.cpython-38.pyc
crawlite/core/http/__pycache__/adapters.cpython-310.pyc
crawlite/core/http/__pycache__/adaptors.cpython-310.pyc
crawlite/core/http/__pycache__/cached_request.cpython-310.pyc
crawlite/core/http/__pycache__/cached_request.cpython-38.pyc
crawlite/core/http/__pycache__/curl.cpython-310.pyc
crawlite/core/http/__pycache__/exceptions.cpython-310.pyc
crawlite/core/http/__pycache__/exceptions.cpython-38.pyc
crawlite/core/http/__pycache__/helper.cpython-310.pyc
crawlite/core/http/__pycache__/utils.cpython-310.pyc
crawlite/core/http/__pycache__/utils.cpython-38.pyc
crawlite/core/parser/__init__.py
crawlite/core/parser/exceptions.py
crawlite/core/parser/soup.py
crawlite/core/parser/__pycache__/__init__.cpython-310.pyc
crawlite/core/parser/__pycache__/__init__.cpython-38.pyc
crawlite/core/parser/__pycache__/exceptions.cpython-310.pyc
crawlite/core/parser/__pycache__/exceptions.cpython-38.pyc
crawlite/core/parser/__pycache__/soup.cpython-310.pyc
crawlite/core/parser/__pycache__/soup.cpython-38.pyc
crawlite/core/parser/__pycache__/utils.cpython-310.pyc
crawlite/core/parser/__pycache__/utils.cpython-38.pyc
crawlite/crawler/__init__.py
crawlite/crawler/actions.py
crawlite/crawler/base.py
crawlite/crawler/event.py
