Metadata-Version: 2.1
Name: crawlite
Version: 0.1.3
Summary: Scraping library by crawling link patterns, url and parsing
Home-page: UNKNOWN
Author: HS Moon
Author-email: pbr112@naver.com
License: MIT
Keywords: crawlite
Platform: UNKNOWN
Classifier: Programming Language :: Python :: 3.8
Classifier: Programming Language :: Python :: 3.9
Classifier: Programming Language :: Python :: 3.10
Provides-Extra: dev
Provides-Extra: test
